anemoi/__init__.py
anemoi/_version.py
anemoi/mast.py
anemoi/mast_data.py
anemoi/reference.py
anemoi/site.py
anemoi/analysis/__init__.py
anemoi/analysis/correlate.py
anemoi/analysis/shear.py
anemoi/analysis/weibull.py
anemoi/analysis/wind_rose.py
anemoi/io/__init__.py
anemoi/io/database.py
anemoi/io/read_data.py
anemoi/io/references.py
anemoi/io/write_data.py
anemoi/plotting/__init__.py
anemoi/plotting/correlate.py
anemoi/plotting/mast_data.py
anemoi/plotting/plotting.py
anemoi/plotting/references.py
anemoi/plotting/shear.py
anemoi/utils/__init__.py
anemoi/utils/gis.py
anemoi/utils/mast_data.py
anemoi-0.0.61.dist-info/METADATA
anemoi-0.0.61.dist-info/RECORD
anemoi-0.0.61.dist-info/WHEEL
anemoi-0.0.61.dist-info/top_level.txt
