Metadata-Version: 2.1
Name: anemoi
Version: 0.0.61
Summary: EDF wind data analysis package
Home-page: http://github.com/coryjog/anemoi
Author: Cory Jog
Author-email: cory.jog@edf-re.com
License: MIT License
Project-URL: Source, https://github.com/coryjog/anemoi
Project-URL: Documentation, https://coryjog.github.io/anemoi/
Project-URL: Tracker, https://github.com/coryjog/anemoi/issues
Keywords: wind data analysis EDF
Platform: UNKNOWN
Classifier: Development Status :: 3 - Alpha
Classifier: Intended Audience :: Developers
Classifier: Topic :: Software Development :: Build Tools
Classifier: License :: OSI Approved :: MIT License
Classifier: Programming Language :: Python :: 3
Requires-Python: >=3
Requires-Dist: pandas
Requires-Dist: numpy
Requires-Dist: scipy
Requires-Dist: matplotlib
Requires-Dist: plotly
Requires-Dist: pyodbc
Requires-Dist: statsmodels
